plan_view/__init__.py
plan_view/cli.py
plan_view/commands/__init__.py
plan_view/commands/edit.py
plan_view/commands/view.py
plan_view/decorators.py
plan_view/formatting.py
plan_view/io.py
plan_view/plan.schema.json
plan_view/state.py
plan_view-1.3.0.dist-info/WHEEL
plan_view-1.3.0.dist-info/entry_points.txt
plan_view-1.3.0.dist-info/METADATA
plan_view-1.3.0.dist-info/RECORD
