Metadata-Version: 2.4
Name: plan-view
Version: 1.3.0
Summary: Pretty print plan.json for task tracking
Keywords: cli,plan,task-tracking,ai-agents
Author: Jacob Coffee
Author-email: Jacob Coffee <jacob@z7x.org>
License-Expression: MIT
Classifier: Development Status :: 4 - Beta
Classifier: Environment :: Console
Classifier: Intended Audience :: Developers
Classifier: License :: OSI Approved :: MIT License
Classifier: Programming Language :: Python :: 3
Classifier: Programming Language :: Python :: 3.14
Classifier: Topic :: Software Development :: Build Tools
Classifier: Typing :: Typed
Requires-Dist: jsonschema>=4.23
Requires-Python: >=3.14
Project-URL: Changelog, https://github.com/JacobCoffee/pv/releases/
Project-URL: Homepage, https://github.com/JacobCoffee/pv
Project-URL: Issue Tracker, https://github.com/JacobCoffee/pv/issues
Project-URL: Repository, https://github.com/JacobCoffee/pv
